{
  "_class": "shapeGroup",
  "booleanOperation": -1,
  "clippingMaskMode": 0,
  "do_objectID": "0E1DD3DD-2724-480F-831D-2C6F783C7476",
  "exportOptions": {
    "_class": "exportOptions",
    "do_objectID": "C5D1334C-516B-4EBA-9A80-CE808A02E720",
    "exportFormats": [
    ],
    "includedLayerIds": [
    ],
    "layerOptions": 0,
    "shouldTrim": false
  },
  "frame": {
    "_class": "rect",
    "constrainProportions": false,
    "do_objectID": "90CC3118-933F-4CF8-8295-EBBFC7E4137F",
    "height": 108,
    "width": 124.9441022424699,
    "x": 5.055897757530081,
    "y": 0
  },
  "hasClickThrough": false,
  "hasClippingMask": false,
  "isFixedToViewport": false,
  "isFlippedHorizontal": false,
  "isFlippedVertical": false,
  "isLocked": false,
  "isVisible": true,
  "layerListExpandedType": 2,
  "layers": [
    {
      "class": "shapePath",
      "id": "E2885C16-0FB3-4D6F-A8FC-ACCB19DAD76B"
    },
    {
      "class": "rectangle",
      "id": "6D45CA1A-D6B5-4FBA-936A-76C2D5452DFD"
    }
  ],
  "name": "Combined Shape",
  "nameIsFixed": false,
  "resizingConstraint": 63,
  "resizingType": 0,
  "rotation": 0,
  "sharedStyleID": "97287744-6412-4816-9CD2-5AD8CBD7645B",
  "shouldBreakMaskChain": false,
  "style": {
    "_class": "style",
    "do_objectID": "1E6EA23D-A16A-499F-801A-05EF589D79F9",
    "endMarkerType": 0,
    "fills": [
      {
        "_class": "fill",
        "color": {
          "_class": "color",
          "alpha": 1,
          "blue": 0.847,
          "green": 0.847,
          "red": 0.847
        },
        "fillType": 1,
        "gradient": {
          "_class": "gradient",
          "elipseLength": 0,
          "from": "{0.27291411885423489, 0.42925963401384115}",
          "gradientType": 0,
          "stops": [
            {
              "_class": "gradientStop",
              "color": {
                "_class": "color",
                "alpha": 1,
                "blue": 0.3098039215686275,
                "green": 0.3058823529411765,
                "red": 1
              },
              "position": 0
            },
            {
              "_class": "gradientStop",
              "color": {
                "_class": "color",
                "alpha": 1,
                "blue": 0.4392156862745098,
                "green": 0.8156862745098039,
                "red": 1
              },
              "position": 1
            }
          ],
          "to": "{0.93493104934774252, 0.14467903144709293}"
        },
        "isEnabled": true,
        "noiseIndex": 0,
        "noiseIntensity": 0,
        "patternFillType": 0,
        "patternTileScale": 1
      }
    ],
    "miterLimit": 10,
    "startMarkerType": 0,
    "windingRule": 1
  },
  "windingRule": 1
}