{
  "_class": "oval",
  "booleanOperation": -1,
  "clippingMaskMode": 0,
  "do_objectID": "A1E97465-22C1-4956-8F51-B8BE3FD1FE7F",
  "edited": false,
  "exportOptions": {
    "_class": "exportOptions",
    "do_objectID": "0D9A0641-B909-4E09-AA09-7C738B3611B0",
    "exportFormats": [
    ],
    "includedLayerIds": [
    ],
    "layerOptions": 0,
    "shouldTrim": false
  },
  "frame": {
    "_class": "rect",
    "constrainProportions": true,
    "do_objectID": "8B92C562-8E64-4244-A9B2-17731001623F",
    "height": 31.7135593220339,
    "width": 31.68470332063147,
    "x": 26.99067319905643,
    "y": 22.61059322033887
  },
  "hasClippingMask": false,
  "isClosed": true,
  "isFixedToViewport": false,
  "isFlippedHorizontal": false,
  "isFlippedVertical": false,
  "isLocked": false,
  "isVisible": true,
  "layerListExpandedType": 0,
  "name": "Oval 2 Copy 26",
  "nameIsFixed": false,
  "pointRadiusBehaviour": 1,
  "points": [
    {
      "_class": "curvePoint",
      "cornerRadius": 0,
      "curveFrom": "{0.77614237490000004, 1}",
      "curveMode": 2,
      "curveTo": "{0.22385762510000001, 1}",
      "hasCurveFrom": true,
      "hasCurveTo": true,
      "point": "{0.5, 1}"
    },
    {
      "_class": "curvePoint",
      "cornerRadius": 0,
      "curveFrom": "{1, 0.22385762510000001}",
      "curveMode": 2,
      "curveTo": "{1, 0.77614237490000004}",
      "hasCurveFrom": true,
      "hasCurveTo": true,
      "point": "{1, 0.5}"
    },
    {
      "_class": "curvePoint",
      "cornerRadius": 0,
      "curveFrom": "{0.22385762510000001, 0}",
      "curveMode": 2,
      "curveTo": "{0.77614237490000004, 0}",
      "hasCurveFrom": true,
      "hasCurveTo": true,
      "point": "{0.5, 0}"
    },
    {
      "_class": "curvePoint",
      "cornerRadius": 0,
      "curveFrom": "{0, 0.77614237490000004}",
      "curveMode": 2,
      "curveTo": "{0, 0.22385762510000001}",
      "hasCurveFrom": true,
      "hasCurveTo": true,
      "point": "{0, 0.5}"
    }
  ],
  "resizingConstraint": 63,
  "resizingType": 0,
  "rotation": 0,
  "shouldBreakMaskChain": false,
  "style": {
    "_class": "style",
    "blur": {
      "_class": "blur",
      "center": "{0.5, 0.5}",
      "do_objectID": "09DF8DD2-679D-4FAD-9EBE-8FB238F67507",
      "isEnabled": false,
      "motionAngle": 0,
      "radius": 3.078409090909092,
      "saturation": 1,
      "type": 0
    },
    "borders": [
      {
        "_class": "border",
        "color": {
          "_class": "color",
          "alpha": 1,
          "blue": 0.592,
          "green": 0.592,
          "red": 0.592
        },
        "fillType": 0,
        "isEnabled": false,
        "position": 0,
        "thickness": 0.5
      }
    ],
    "contextSettings": {
      "_class": "graphicsContextSettings",
      "blendMode": 0,
      "do_objectID": "D8024DFC-56E1-478B-9438-B6FC901E8019",
      "opacity": 0.1000000014901161
    },
    "do_objectID": "030BF354-E35A-475E-823C-BF5DAD67AA07",
    "endMarkerType": 0,
    "fills": [
      {
        "_class": "fill",
        "color": {
          "_class": "color",
          "alpha": 1,
          "blue": 1,
          "green": 1,
          "red": 1
        },
        "fillType": 0,
        "gradient": {
          "_class": "gradient",
          "elipseLength": 0,
          "from": "{-0.3193471959287017, -0.46121210387432759}",
          "gradientType": 0,
          "stops": [
            {
              "_class": "gradientStop",
              "color": {
                "_class": "color",
                "alpha": 1,
                "blue": 0.7799213435374149,
                "green": 0.5434584488190795,
                "red": 0.5582775398773446
              },
              "position": 0
            },
            {
              "_class": "gradientStop",
              "color": {
                "_class": "color",
                "alpha": 1,
                "blue": 0.9725499574829932,
                "green": 0.3169114513838897,
                "red": 0.8225592870150084
              },
              "position": 1
            }
          ],
          "to": "{1.1995307215370894, 1.2040669992614113}"
        },
        "isEnabled": true,
        "noiseIndex": 0,
        "noiseIntensity": 0,
        "patternFillType": 1,
        "patternTileScale": 1
      }
    ],
    "miterLimit": 10,
    "startMarkerType": 0,
    "windingRule": 1
  }
}