{
  "_class": "artboard",
  "backgroundColor": {
    "_class": "color",
    "alpha": 1,
    "blue": 0.7593005952380952,
    "green": 0.7593005952380952,
    "red": 0.7593005952380952
  },
  "booleanOperation": -1,
  "clippingMaskMode": 0,
  "do_objectID": "C0297577-0ED1-49B9-9DED-55FD42731483",
  "exportOptions": {
    "_class": "exportOptions",
    "exportFormats": [
      {
        "_class": "exportFormat",
        "absoluteSize": 0,
        "fileFormat": "png",
        "name": "",
        "namingScheme": 0,
        "scale": 1,
        "visibleScaleType": 0
      }
    ],
    "includedLayerIds": [
    ],
    "layerOptions": 0,
    "shouldTrim": false
  },
  "frame": {
    "_class": "rect",
    "constrainProportions": false,
    "height": 192,
    "width": 192,
    "x": 1364,
    "y": 3562
  },
  "hasBackgroundColor": false,
  "hasClickThrough": true,
  "hasClippingMask": false,
  "horizontalRulerData": {
    "_class": "rulerData",
    "base": 0,
    "guides": [
    ]
  },
  "includeBackgroundColorInExport": true,
  "includeInCloudUpload": true,
  "isFixedToViewport": false,
  "isFlippedHorizontal": false,
  "isFlippedVertical": false,
  "isFlowHome": false,
  "isLocked": false,
  "isVisible": true,
  "layerListExpandedType": 2,
  "layers": [
    {
      "class": "symbolInstance",
      "id": "F6F0026F-D610-405A-99B9-489465BB2E90"
    },
    {
      "class": "oval",
      "id": "508A6FC3-3D5F-4B3A-9960-32F91CAA6316"
    },
    {
      "class": "symbolInstance",
      "id": "B5739AEF-E535-49DE-9963-B4650EABB78E"
    },
    {
      "class": "shapeGroup",
      "id": "B57685D6-2ACF-4C84-80A3-21E1C3E80C2E"
    },
    {
      "class": "shapePath",
      "id": "11DE403E-A8A7-43CC-9340-E7F7E5D68D1C"
    }
  ],
  "name": "固定时间",
  "nameIsFixed": true,
  "resizesContent": false,
  "resizingConstraint": 63,
  "resizingType": 0,
  "rotation": 0,
  "shouldBreakMaskChain": true,
  "style": {
    "_class": "style",
    "endMarkerType": 0,
    "miterLimit": 10,
    "startMarkerType": 0,
    "windingRule": 1
  },
  "userInfo": {
    "io.magicsketch.mirror": {
      "highestQuality": 2
    }
  },
  "verticalRulerData": {
    "_class": "rulerData",
    "base": 0,
    "guides": [
    ]
  }
}